<?xml version="1.0" encoding="UTF-8"?>
<persistence xmlns="http://java.sun.com/xml/ns/persistence" version="2.0">

    <persistence-unit name="ch.bfh.jarchitects.filmbiblio.domain">
        <class>ch.bfh.jarchitects.filmbiblio.model.User</class>
        <class>ch.bfh.jarchitects.filmbiblio.model.Rent</class>
        <class>ch.bfh.jarchitects.filmbiblio.model.Dvd</class>
        <class>ch.bfh.jarchitects.filmbiblio.model.MovieReview</class>
        <class>ch.bfh.jarchitects.filmbiblio.model.Movie</class>
        <class>ch.bfh.jarchitects.filmbiblio.model.WaitingList</class>
    </persistence-unit>
</persistence>
